facebook_login/__init__.py
facebook_login/admin.py
facebook_login/auth_backends.py
facebook_login/exceptions.py
facebook_login/models.py
facebook_login/schema.py
facebook_login/settings.py
facebook_login/utils.py
facebook_login/migrations/0001_initial.py
facebook_login/migrations/0002_auto_20180920_0336.py
facebook_login/migrations/__init__.py
facebook_login/tests/__init__.py
facebook_login/tests/runserver_settings.py
facebook_login/tests/test_auth_backends.py
facebook_login/tests/test_exceptions.py
facebook_login/tests/test_models.py
facebook_login/tests/test_schema.py
facebook_login/tests/test_settings.py
facebook_login/tests/test_utils.py
facebook_login/tests/urls.py
facebook_login/tests/utils.py
django_facebook_login-5.1.2.dist-info/LICENSE
django_facebook_login-5.1.2.dist-info/METADATA
django_facebook_login-5.1.2.dist-info/WHEEL
django_facebook_login-5.1.2.dist-info/top_level.txt
django_facebook_login-5.1.2.dist-info/RECORD
