Metadata-Version: 2.1
Name: django-facebook-login
Version: 5.1.2
Summary: A GraphQL endpoint and authentication backend to signup or login a valid user access token from Facebook
Home-page: https://github.com/theartling/django-facebook-login/
Author: Martin Brochhaus
Author-email: mbrochh@gmail.com
License: MIT License
Classifier: Environment :: Web Environment
Classifier: Framework :: Django
Classifier: Framework :: Django :: 2.0
Classifier: Intended Audience :: Developers
Classifier: License :: OSI Approved :: MIT License
Classifier: Operating System :: OS Independent
Classifier: Programming Language :: Python
Classifier: Programming Language :: Python :: 3.6
Classifier: Topic :: Internet :: WWW/HTTP
Classifier: Topic :: Internet :: WWW/HTTP :: Dynamic Content
License-File: LICENSE
Requires-Dist: django (>=4)
Requires-Dist: graphene-django (>=3)
Provides-Extra: dev
Requires-Dist: pytest ; extra == 'dev'
Requires-Dist: pytest-django ; extra == 'dev'
Requires-Dist: pytest-cov ; extra == 'dev'
Requires-Dist: responses ; extra == 'dev'
Requires-Dist: fabric ; extra == 'dev'
Requires-Dist: mixer ; extra == 'dev'
